openfoamtools/__init__.py
openfoamtools-0.1.0.dist-info/LICENSE
openfoamtools-0.1.0.dist-info/METADATA
openfoamtools-0.1.0.dist-info/WHEEL
openfoamtools-0.1.0.dist-info/RECORD
