Metadata-Version: 2.1
Name: openfoamtools
Version: 0.1.0
Summary: Auxilary Tools for pre and post processing tasks for openFOAM-9
License: MIT
Author: Guillermo Ibarra
Author-email: guillermoibarra@gmail.com
Requires-Python: >=3.10,<4.0
Classifier: Development Status :: 1 - Planning
Classifier: Intended Audience :: Science/Research
Classifier: License :: OSI Approved :: MIT License
Classifier: Programming Language :: Python :: 3
Classifier: Programming Language :: Python :: 3.10
Classifier: Programming Language :: Python :: 3.11
Classifier: Topic :: Scientific/Engineering
